donk/__init__.py
donk/__main__.py
donk/main.py
donk/param_types.py
donk-1.1.0.dist-info/licenses/LICENSE
donk-1.1.0.dist-info/METADATA
donk-1.1.0.dist-info/WHEEL
donk-1.1.0.dist-info/entry_points.txt
donk-1.1.0.dist-info/top_level.txt
donk-1.1.0.dist-info/RECORD
