Metadata-Version: 2.4
Name: donk
Version: 1.1.0
Summary: donk is a minimal version management tool for pyproject.toml files
Requires-Python: >=3.10
License-File: LICENSE
Requires-Dist: click>=8.1.8
Requires-Dist: semver>=3.0.4
Requires-Dist: tomlkit>=0.13.2
Dynamic: license-file
